README.rst
setup.py
roc/__init__.py
roc/__main__.py
roc/cli.py
roc/client.py
roc/loader.py
roc/remote.py
roc/server.py
roc.egg-info/PKG-INFO
roc.egg-info/SOURCES.txt
roc.egg-info/dependency_links.txt
roc.egg-info/not-zip-safe
roc.egg-info/top_level.txt