Metadata-Version: 1.0
Name: roc
Version: 0.3.2
Summary: XMLRPC with classes
Home-page: https://github.com/peterdemin/python-roc
Author: Peter Demin
Author-email: poslano@gmail.com
License: BSD
Keywords: roc xml rpc fitnesse slim vagrant
Platform: UNKNOWN
Classifier: Development Status :: 2 - Pre-Alpha
Classifier: Intended Audience :: Developers
Classifier: License :: OSI Approved :: BSD License
Classifier: Natural Language :: English
Classifier: Programming Language :: Python :: 2
Classifier: Programming Language :: Python :: 2.6
Classifier: Programming Language :: Python :: 2.7
Classifier: Programming Language :: Python :: 3
Classifier: Programming Language :: Python :: 3.2
Classifier: Programming Language :: Python :: 3.3
